src/__init__.py
src/__main__.py
src/cache.py
src/main.py
src/api/__init__.py
src/api/client.py
src/api/site_manager_client.py
src/config/__init__.py
src/config/config.py
src/models/__init__.py
src/models/acl.py
src/models/backup.py
src/models/client.py
src/models/device.py
src/models/dpi.py
src/models/firewall_policy.py
src/models/firewall_zone.py
src/models/network.py
src/models/qos_profile.py
src/models/radius.py
src/models/reference_data.py
src/models/site.py
src/models/site_manager.py
src/models/topology.py
src/models/traffic_flow.py
src/models/traffic_matching_list.py
src/models/voucher.py
src/models/vpn.py
src/models/wan.py
src/models/zbf_matrix.py
src/resources/__init__.py
src/resources/clients.py
src/resources/devices.py
src/resources/networks.py
src/resources/site_manager.py
src/resources/sites.py
src/tools/__init__.py
src/tools/acls.py
src/tools/application.py
src/tools/backups.py
src/tools/client_management.py
src/tools/clients.py
src/tools/device_control.py
src/tools/devices.py
src/tools/dpi.py
src/tools/dpi_tools.py
src/tools/firewall.py
src/tools/firewall_policies.py
src/tools/firewall_zones.py
src/tools/network_config.py
src/tools/networks.py
src/tools/port_forwarding.py
src/tools/qos.py
src/tools/radius.py
src/tools/reference_data.py
src/tools/site_manager.py
src/tools/site_vpn.py
src/tools/sites.py
src/tools/topology.py
src/tools/traffic_flows.py
src/tools/traffic_matching_lists.py
src/tools/vouchers.py
src/tools/vpn.py
src/tools/wans.py
src/tools/wifi.py
src/tools/zbf_matrix.py
src/utils/__init__.py
src/utils/audit.py
src/utils/exceptions.py
src/utils/helpers.py
src/utils/logger.py
src/utils/sanitize.py
src/utils/validators.py
src/webhooks/__init__.py
src/webhooks/handlers.py
src/webhooks/receiver.py
unifi_mcp_server-0.2.1.dist-info/METADATA
unifi_mcp_server-0.2.1.dist-info/WHEEL
unifi_mcp_server-0.2.1.dist-info/entry_points.txt
unifi_mcp_server-0.2.1.dist-info/licenses/LICENSE
unifi_mcp_server-0.2.1.dist-info/RECORD
